{"cameraMode":{"drawMode":0,"name":"Shaded","section":"Shading Mode"},"sceneLighting":false,"audioPlay":false,"sceneViewState":{"showFog":true,"showMaterialUpdate":false,"showSkybox":true,"showFlares":true,"showImageEffects":true,"showParticleSystems":true,"showVisualEffectGraphs":true,"m_FxEnabled":true},"in2DMode":false,"pivot":{"x":866.7532958984375,"y":-3844.361083984375,"z":2217.49853515625},"rotation":{"x":0.47426140308380129,"y":0.050129227340221408,"z":-0.027066776528954507,"w":0.8785433173179627},"size":2515.795166015625,"orthographic":false}